Metadata-Version: 2.1
Name: mnemonicode
Version: 1.4.5
Summary: A library for encoding binary data as a sequence of english words
Home-page: https://github.com/bwhmather/python-mnemonicode
Author: Ben Mather
Author-email: bwhmather@bwhmather.com
Maintainer: 
License: BSD
Platform: UNKNOWN
Classifier: Development Status :: 5 - Production/Stable
Classifier: Intended Audience :: Developers
Classifier: License :: OSI Approved :: BSD License
Classifier: Operating System :: OS Independent
Classifier: Programming Language :: Python :: 3
Classifier: Programming Language :: Python :: 3.4
Classifier: Programming Language :: Python :: 3.5
Classifier: Programming Language :: Python :: 3.6
Classifier: Programming Language :: Python :: 3.7
Classifier: Programming Language :: Python :: 3.8
Classifier: Programming Language :: Python :: 3 :: Only
